mongodbm/__init__.py
mongodbm/main.py
mongodbm/utils.py
mongodbm/tests/__init__.py
mongodbm-0.0.3.dist-info/LICENSE
mongodbm-0.0.3.dist-info/METADATA
mongodbm-0.0.3.dist-info/WHEEL
mongodbm-0.0.3.dist-info/top_level.txt
mongodbm-0.0.3.dist-info/RECORD
