Metadata-Version: 2.1
Name: mongodbm
Version: 0.0.3
Summary: A python key-value MongoDB database
Home-page: https://github.com/mullenkamp/mongodbm
Author: Mike Kittridge
Author-email: mullenkamp1@gmail.com
License: Apache
Keywords: shelve dbm
Classifier: Development Status :: 3 - Alpha
Classifier: Intended Audience :: Developers
Classifier: License :: OSI Approved :: Apache Software License
Classifier: Programming Language :: Python :: 3.8
Classifier: Programming Language :: Python :: 3.9
License-File: LICENSE
Requires-Dist: pymongo
